feathon/__init__.py
feathon-0.1.0.dev0.dist-info/WHEEL
feathon-0.1.0.dev0.dist-info/METADATA
feathon-0.1.0.dev0.dist-info/RECORD
